py_gamma/__init__.py
py_gamma/cache.py
py_gamma/client.py
py_gamma/config.py
py_gamma/exceptions.py
py_gamma/endpoints/__init__.py
py_gamma/endpoints/base.py
py_gamma/endpoints/comments.py
py_gamma/endpoints/events.py
py_gamma/endpoints/markets.py
py_gamma/endpoints/search.py
py_gamma/endpoints/series.py
py_gamma/endpoints/sports.py
py_gamma/endpoints/tags.py
py_gamma/endpoints/user.py
py_gamma/models/__init__.py
py_gamma/models/base.py
py_gamma/models/comments.py
py_gamma/models/events.py
py_gamma/models/markets.py
py_gamma/models/search.py
py_gamma/models/series.py
py_gamma/models/sports.py
py_gamma/models/tags.py
py_gamma/models/user.py
polymarket_gamma-0.1.2.dist-info/METADATA
polymarket_gamma-0.1.2.dist-info/WHEEL
polymarket_gamma-0.1.2.dist-info/licenses/LICENSE
polymarket_gamma-0.1.2.dist-info/RECORD
