Metadata-Version: 2.4
Name: polymarket-gamma
Version: 0.1.2
Summary: Modern Python SDK for Polymarket Gamma API. Install as 'polymarket-gamma', import as 'py_gamma'.
Project-URL: Homepage, https://github.com/Unipredict/py-gamma
Project-URL: Documentation, https://github.com/Unipredict/py-gamma
Project-URL: Repository, https://github.com/Unipredict/py-gamma.git
Project-URL: Bug Tracker, https://github.com/Unipredict/py-gamma/issues
Project-URL: Changelog, https://github.com/Unipredict/py-gamma/blob/main/CHANGELOG.md
Author-email: Polybacktest Team <team@polybacktest.dev>
License-File: LICENSE
Classifier: Development Status :: 3 - Alpha
Classifier: Intended Audience :: Developers
Classifier: License :: OSI Approved :: MIT License
Classifier: Operating System :: OS Independent
Classifier: Programming Language :: Python :: 3
Classifier: Programming Language :: Python :: 3.11
Classifier: Programming Language :: Python :: 3.12
Classifier: Programming Language :: Python :: 3.13
Classifier: Topic :: Internet :: WWW/HTTP
Classifier: Topic :: Software Development :: Libraries :: Python Modules
Requires-Python: >=3.11
Requires-Dist: cachetools>=6.2.0
Requires-Dist: diskcache>=5.6.0
Requires-Dist: httpx>=0.28.0
Requires-Dist: pydantic>=2.12.0
Requires-Dist: python-dotenv>=1.2.0
Requires-Dist: pyyaml>=6.0
Provides-Extra: dev
Requires-Dist: basedpyright>=1.33.0; extra == 'dev'
Requires-Dist: pre-commit>=3.4.0; extra == 'dev'
Requires-Dist: pytest-asyncio>=0.21.0; extra == 'dev'
Requires-Dist: pytest-cov>=4.1.0; extra == 'dev'
Requires-Dist: pytest>=7.4.0; extra == 'dev'
Requires-Dist: ruff>=0.1.0; extra == 'dev'
Requires-Dist: types-pyyaml>=6.0.0; extra == 'dev'
